[
{
	"L" : 4,
	"nStep" : 15,
	"acceptance" : 0.972937,
	"magnetization" : {"val" : 0.375749, "err" : 0.001047},
	"mag_sq" : {"val" : 0.183048, "err" : 0.000789},
	"deltaH" : {"val" : 0.053991, "err" : 0.000051},
	"exp" : {"val" : 0.998951, "err" : 0.000057}
},
{
	"L" : 4,
	"nStep" : 20,
	"acceptance" : 0.984808,
	"magnetization" : {"val" : 0.375617, "err" : 0.001003},
	"mag_sq" : {"val" : 0.183014, "err" : 0.000763},
	"deltaH" : {"val" : 0.030211, "err" : 0.000028},
	"exp" : {"val" : 0.999045, "err" : 0.000042}
},
{
	"L" : 4,
	"nStep" : 25,
	"acceptance" : 0.990344,
	"magnetization" : {"val" : 0.376529, "err" : 0.001027},
	"mag_sq" : {"val" : 0.183514, "err" : 0.000778},
	"deltaH" : {"val" : 0.019285, "err" : 0.000018},
	"exp" : {"val" : 0.998990, "err" : 0.000036}
},
{
	"L" : 4,
	"nStep" : 30,
	"acceptance" : 0.993327,
	"magnetization" : {"val" : 0.375313, "err" : 0.001018},
	"mag_sq" : {"val" : 0.182760, "err" : 0.000770},
	"deltaH" : {"val" : 0.013373, "err" : 0.000012},
	"exp" : {"val" : 0.999007, "err" : 0.000034}
},
{
	"L" : 4,
	"nStep" : 35,
	"acceptance" : 0.995208,
	"magnetization" : {"val" : 0.374586, "err" : 0.000997},
	"mag_sq" : {"val" : 0.182110, "err" : 0.000753},
	"deltaH" : {"val" : 0.009823, "err" : 0.000009},
	"exp" : {"val" : 0.999015, "err" : 0.000033}
},
{
	"L" : 4,
	"nStep" : 40,
	"acceptance" : 0.996277,
	"magnetization" : {"val" : 0.375760, "err" : 0.000992},
	"mag_sq" : {"val" : 0.182997, "err" : 0.000749},
	"deltaH" : {"val" : 0.007517, "err" : 0.000007},
	"exp" : {"val" : 0.999005, "err" : 0.000032}
},
{
	"L" : 4,
	"nStep" : 45,
	"acceptance" : 0.997105,
	"magnetization" : {"val" : 0.375718, "err" : 0.000977},
	"mag_sq" : {"val" : 0.182976, "err" : 0.000746},
	"deltaH" : {"val" : 0.005939, "err" : 0.000005},
	"exp" : {"val" : 0.999004, "err" : 0.000032}
},
{
	"L" : 4,
	"nStep" : 50,
	"acceptance" : 0.997619,
	"magnetization" : {"val" : 0.375336, "err" : 0.000967},
	"mag_sq" : {"val" : 0.182443, "err" : 0.000736},
	"deltaH" : {"val" : 0.004802, "err" : 0.000005},
	"exp" : {"val" : 0.998998, "err" : 0.000032}
},
{
	"L" : 8,
	"nStep" : 15,
	"acceptance" : 0.925009,
	"magnetization" : {"val" : 0.205246, "err" : 0.001140},
	"mag_sq" : {"val" : 0.058519, "err" : 0.000535},
	"deltaH" : {"val" : 0.151020, "err" : 0.000124},
	"exp" : {"val" : 0.999051, "err" : 0.000145}
},
{
	"L" : 8,
	"nStep" : 20,
	"acceptance" : 0.958131,
	"magnetization" : {"val" : 0.205628, "err" : 0.001110},
	"mag_sq" : {"val" : 0.058686, "err" : 0.000526},
	"deltaH" : {"val" : 0.084026, "err" : 0.000068},
	"exp" : {"val" : 0.998976, "err" : 0.000080}
},
{
	"L" : 8,
	"nStep" : 25,
	"acceptance" : 0.973032,
	"magnetization" : {"val" : 0.205220, "err" : 0.001093},
	"mag_sq" : {"val" : 0.058614, "err" : 0.000512},
	"deltaH" : {"val" : 0.053718, "err" : 0.000044},
	"exp" : {"val" : 0.998986, "err" : 0.000058}
},
{
	"L" : 8,
	"nStep" : 30,
	"acceptance" : 0.981204,
	"magnetization" : {"val" : 0.205227, "err" : 0.001118},
	"mag_sq" : {"val" : 0.058521, "err" : 0.000525},
	"deltaH" : {"val" : 0.037238, "err" : 0.000030},
	"exp" : {"val" : 0.998999, "err" : 0.000045}
},
{
	"L" : 8,
	"nStep" : 35,
	"acceptance" : 0.986118,
	"magnetization" : {"val" : 0.206118, "err" : 0.001161},
	"mag_sq" : {"val" : 0.058979, "err" : 0.000543},
	"deltaH" : {"val" : 0.027355, "err" : 0.000022},
	"exp" : {"val" : 0.999017, "err" : 0.000039}
},
{
	"L" : 8,
	"nStep" : 40,
	"acceptance" : 0.989597,
	"magnetization" : {"val" : 0.205595, "err" : 0.001087},
	"mag_sq" : {"val" : 0.058766, "err" : 0.000506},
	"deltaH" : {"val" : 0.020901, "err" : 0.000017},
	"exp" : {"val" : 0.998995, "err" : 0.000036}
},
{
	"L" : 8,
	"nStep" : 45,
	"acceptance" : 0.991678,
	"magnetization" : {"val" : 0.206748, "err" : 0.001124},
	"mag_sq" : {"val" : 0.059287, "err" : 0.000527},
	"deltaH" : {"val" : 0.016504, "err" : 0.000013},
	"exp" : {"val" : 0.999014, "err" : 0.000035}
},
{
	"L" : 8,
	"nStep" : 50,
	"acceptance" : 0.993198,
	"magnetization" : {"val" : 0.206176, "err" : 0.001100},
	"mag_sq" : {"val" : 0.058930, "err" : 0.000513},
	"deltaH" : {"val" : 0.013360, "err" : 0.000011},
	"exp" : {"val" : 0.999021, "err" : 0.000034}
},
{
	"L" : 12,
	"nStep" : 15,
	"acceptance" : 0.863109,
	"magnetization" : {"val" : 0.125294, "err" : 0.000993},
	"mag_sq" : {"val" : 0.023044, "err" : 0.000314},
	"deltaH" : {"val" : 0.278738, "err" : 0.000220},
	"exp" : {"val" : 0.999158, "err" : 0.000285}
},
{
	"L" : 12,
	"nStep" : 20,
	"acceptance" : 0.923521,
	"magnetization" : {"val" : 0.125096, "err" : 0.000993},
	"mag_sq" : {"val" : 0.023115, "err" : 0.000322},
	"deltaH" : {"val" : 0.154264, "err" : 0.000125},
	"exp" : {"val" : 0.998833, "err" : 0.000151}
},
{
	"L" : 12,
	"nStep" : 25,
	"acceptance" : 0.951161,
	"magnetization" : {"val" : 0.124652, "err" : 0.000956},
	"mag_sq" : {"val" : 0.022952, "err" : 0.000308},
	"deltaH" : {"val" : 0.098330, "err" : 0.000077},
	"exp" : {"val" : 0.998871, "err" : 0.000093}
},
{
	"L" : 12,
	"nStep" : 30,
	"acceptance" : 0.965864,
	"magnetization" : {"val" : 0.126088, "err" : 0.000915},
	"mag_sq" : {"val" : 0.023274, "err" : 0.000293},
	"deltaH" : {"val" : 0.068013, "err" : 0.000055},
	"exp" : {"val" : 0.998992, "err" : 0.000067}
},
{
	"L" : 12,
	"nStep" : 35,
	"acceptance" : 0.975133,
	"magnetization" : {"val" : 0.124913, "err" : 0.000939},
	"mag_sq" : {"val" : 0.023008, "err" : 0.000301},
	"deltaH" : {"val" : 0.049915, "err" : 0.000040},
	"exp" : {"val" : 0.999000, "err" : 0.000053}
},
{
	"L" : 12,
	"nStep" : 40,
	"acceptance" : 0.980865,
	"magnetization" : {"val" : 0.125160, "err" : 0.000910},
	"mag_sq" : {"val" : 0.023053, "err" : 0.000293},
	"deltaH" : {"val" : 0.038234, "err" : 0.000030},
	"exp" : {"val" : 0.998999, "err" : 0.000046}
},
{
	"L" : 12,
	"nStep" : 45,
	"acceptance" : 0.984892,
	"magnetization" : {"val" : 0.126232, "err" : 0.000930},
	"mag_sq" : {"val" : 0.023469, "err" : 0.000300},
	"deltaH" : {"val" : 0.030176, "err" : 0.000024},
	"exp" : {"val" : 0.999011, "err" : 0.000041}
},
{
	"L" : 12,
	"nStep" : 50,
	"acceptance" : 0.987735,
	"magnetization" : {"val" : 0.125930, "err" : 0.000979},
	"mag_sq" : {"val" : 0.023421, "err" : 0.000316},
	"deltaH" : {"val" : 0.024440, "err" : 0.000019},
	"exp" : {"val" : 0.999007, "err" : 0.000038}
},
{
	"L" : 14,
	"nStep" : 15,
	"acceptance" : 0.827919,
	"magnetization" : {"val" : 0.101060, "err" : 0.000897},
	"mag_sq" : {"val" : 0.015351, "err" : 0.000242},
	"deltaH" : {"val" : 0.353929, "err" : 0.000297},
	"exp" : {"val" : 0.998570, "err" : 0.000391}
},
{
	"L" : 14,
	"nStep" : 20,
	"acceptance" : 0.903552,
	"magnetization" : {"val" : 0.101778, "err" : 0.000848},
	"mag_sq" : {"val" : 0.015589, "err" : 0.000232},
	"deltaH" : {"val" : 0.194583, "err" : 0.000154},
	"exp" : {"val" : 0.998914, "err" : 0.000187}
},
{
	"L" : 14,
	"nStep" : 25,
	"acceptance" : 0.938503,
	"magnetization" : {"val" : 0.101862, "err" : 0.000815},
	"mag_sq" : {"val" : 0.015467, "err" : 0.000221},
	"deltaH" : {"val" : 0.123918, "err" : 0.000100},
	"exp" : {"val" : 0.998934, "err" : 0.000117}
},
{
	"L" : 14,
	"nStep" : 30,
	"acceptance" : 0.957324,
	"magnetization" : {"val" : 0.102061, "err" : 0.000802},
	"mag_sq" : {"val" : 0.015552, "err" : 0.000216},
	"deltaH" : {"val" : 0.085756, "err" : 0.000068},
	"exp" : {"val" : 0.999007, "err" : 0.000083}
},
{
	"L" : 14,
	"nStep" : 35,
	"acceptance" : 0.968736,
	"magnetization" : {"val" : 0.102003, "err" : 0.000857},
	"mag_sq" : {"val" : 0.015606, "err" : 0.000233},
	"deltaH" : {"val" : 0.062790, "err" : 0.000049},
	"exp" : {"val" : 0.998953, "err" : 0.000063}
},
{
	"L" : 14,
	"nStep" : 40,
	"acceptance" : 0.975763,
	"magnetization" : {"val" : 0.102236, "err" : 0.000813},
	"mag_sq" : {"val" : 0.015662, "err" : 0.000219},
	"deltaH" : {"val" : 0.048111, "err" : 0.000039},
	"exp" : {"val" : 0.999015, "err" : 0.000054}
},
{
	"L" : 14,
	"nStep" : 45,
	"acceptance" : 0.980688,
	"magnetization" : {"val" : 0.100599, "err" : 0.000822},
	"mag_sq" : {"val" : 0.015250, "err" : 0.000222},
	"deltaH" : {"val" : 0.038009, "err" : 0.000030},
	"exp" : {"val" : 0.998963, "err" : 0.000045}
},
{
	"L" : 14,
	"nStep" : 50,
	"acceptance" : 0.984468,
	"magnetization" : {"val" : 0.102779, "err" : 0.000857},
	"mag_sq" : {"val" : 0.015803, "err" : 0.000234},
	"deltaH" : {"val" : 0.030764, "err" : 0.000025},
	"exp" : {"val" : 0.998965, "err" : 0.000041}
}
]
